pyempfin/__init__.py
pyempfin/datautils.py
pyempfin/datetimeutils.py
pyempfin/dfutils.py
pyempfin/ffi.py
pyempfin/finutils.py
pyempfin/htmloutput.py
pyempfin/logger.py
pyempfin/sqlutils.py
pyempfin/xsap.py
pyempfin-0.1.5.dist-info/licenses/LICENSE.txt
pyempfin-0.1.5.dist-info/METADATA
pyempfin-0.1.5.dist-info/WHEEL
pyempfin-0.1.5.dist-info/top_level.txt
pyempfin-0.1.5.dist-info/RECORD
