Metadata-Version: 2.4
Name: pyempfin
Version: 0.1.5
Summary: Helper functions for empirical finance research
Home-page: https://github.com/flcong/pyempfin
Author: Francis Cong
Author-email: flcong@outlook.com
License: MIT
License-File: LICENSE.txt
Requires-Dist: numpy
Requires-Dist: pandas
Requires-Dist: numba
Requires-Dist: tabulate
Requires-Dist: joblib
Requires-Dist: scipy
Dynamic: author
Dynamic: license
Dynamic: license-file
Dynamic: requires-dist
Dynamic: summary
